fathom_web/__init__.py
fathom_web/accuracy.py
fathom_web/fathom.zip
fathom_web/utils.py
fathom_web/vectorizer.py
fathom_web/commands/__init__.py
fathom_web/commands/extract.py
fathom_web/commands/fox.py
fathom_web/commands/histogram.py
fathom_web/commands/label.py
fathom_web/commands/list.py
fathom_web/commands/pick.py
fathom_web/commands/serve.py
fathom_web/commands/test.py
fathom_web/commands/train.py
fathom_web-3.7.1.dist-info/METADATA
fathom_web-3.7.1.dist-info/WHEEL
fathom_web-3.7.1.dist-info/dependency_links.txt
fathom_web-3.7.1.dist-info/entry_points.txt
fathom_web-3.7.1.dist-info/top_level.txt
fathom_web-3.7.1.dist-info/RECORD
